tushare_strategy/__init__.py
tushare_strategy-0.1.0.dist-info/METADATA
tushare_strategy-0.1.0.dist-info/WHEEL
tushare_strategy-0.1.0.dist-info/RECORD
